diku_tools/__init__.py
diku_tools/calendars.py
diku_tools/canvas_session.py
diku_tools/course.py
diku_tools/encryption.py
diku_tools/tools.py
diku_tools-1.0.2.dist-info/METADATA
diku_tools-1.0.2.dist-info/RECORD
diku_tools-1.0.2.dist-info/WHEEL
diku_tools-1.0.2.dist-info/top_level.txt
