Metadata-Version: 2.1
Name: diku-tools
Version: 1.0.2
Summary: Python tools for DIKU related apps
Home-page: UNKNOWN
Author: Juulsgaard
Author-email: frederikjs1@hotmail.com
License: UNKNOWN
Platform: UNKNOWN
Classifier: Programming Language :: Python :: 3
Classifier: License :: OSI Approved :: MIT License
Classifier: Operating System :: OS Independent
